llama_index/packs/raptor/__init__.py
llama_index/packs/raptor/base.py
llama_index/packs/raptor/clustering.py
llama_index_packs_raptor-0.4.1.dist-info/METADATA
llama_index_packs_raptor-0.4.1.dist-info/WHEEL
llama_index_packs_raptor-0.4.1.dist-info/licenses/LICENSE
llama_index_packs_raptor-0.4.1.dist-info/RECORD
