Metadata-Version: 2.4
Name: llama-index-packs-raptor
Version: 0.4.1
Summary: llama-index packs raptor integration
Author-email: Logan Markewich <logan@llamaindex.ai>
License-Expression: MIT
License-File: LICENSE
Keywords: cluster,raptor,retrieval
Requires-Python: <4,>=3.10
Requires-Dist: llama-index-core<0.15,>=0.13.0
Requires-Dist: llama-index-llms-openai<0.6,>=0.5.0
Requires-Dist: numba<1,>=0.61.2
Requires-Dist: numpy<2.3,>=2.2
Requires-Dist: scikit-learn
Requires-Dist: umap-learn>=0.5.5
